pyNutTools/__init__.py
pyNutTools/_lib.py
pyNutTools/nutDataframe.py
pyNutTools/nutDate.py
pyNutTools/nutOther.py
pynut_tools-3.1.1.dist-info/LICENSE
pynut_tools-3.1.1.dist-info/METADATA
pynut_tools-3.1.1.dist-info/WHEEL
pynut_tools-3.1.1.dist-info/top_level.txt
pynut_tools-3.1.1.dist-info/RECORD
