Metadata-Version: 2.1
Name: pynut-tools
Version: 3.1.1
Summary: Function easing life :)
Home-page: https://github.com/Laurent-Tupin/pynut_tools
Author: Laurent Tupin
Author-email: laurent.tupinn@gmail.com
License: Copyright 2022-2035
Platform: UNKNOWN
Classifier: License :: Free For Home Use
Classifier: Programming Language :: Python :: 3
Classifier: Programming Language :: Python :: 3.9
License-File: LICENSE
Requires-Dist: pandas (==1.5.3)
Requires-Dist: datefinder (==0.7.3)
